{
  "indexes": [
    {
      "collectionGroup": "aiAssistCache",
      "queryScope": "COLLECTION",
      "fields": [
        { "fieldPath": "userId", "order": "ASCENDING" },
        { "fieldPath": "type", "order": "ASCENDING" },
        { "fieldPath": "generatedAt", "order": "DESCENDING" }
      ]
    },
    {
      "collectionGroup": "aiAssistCache",
      "queryScope": "COLLECTION",
      "fields": [
        { "fieldPath": "userId", "order": "ASCENDING" },
        { "fieldPath": "expiresAt", "order": "ASCENDING" }
      ]
    },
    {
      "collectionGroup": "aiAssistCache",
      "queryScope": "COLLECTION",
      "fields": [
        { "fieldPath": "expiresAt", "order": "ASCENDING" }
      ]
    },
    {
      "collectionGroup": "aiAssistBehaviorData",
      "queryScope": "COLLECTION",
      "fields": [
        { "fieldPath": "userId", "order": "ASCENDING" },
        { "fieldPath": "createdAt", "order": "DESCENDING" }
      ]
    },
    {
      "collectionGroup": "aiInsights",
      "queryScope": "COLLECTION",
      "fields": [
        { "fieldPath": "userId", "order": "ASCENDING" },
        { "fieldPath": "type", "order": "ASCENDING" },
        { "fieldPath": "createdAt", "order": "DESCENDING" }
      ]
    },
    {
      "collectionGroup": "aiInsights",
      "queryScope": "COLLECTION",
      "fields": [
        { "fieldPath": "userId", "order": "ASCENDING" },
        { "fieldPath": "priority", "order": "ASCENDING" },
        { "fieldPath": "createdAt", "order": "DESCENDING" }
      ]
    },
    {
      "collectionGroup": "aiInsights",
      "queryScope": "COLLECTION",
      "fields": [
        { "fieldPath": "userId", "order": "ASCENDING" },
        { "fieldPath": "expiresAt", "order": "ASCENDING" }
      ]
    },
    {
      "collectionGroup": "aiSafetyLogs",
      "queryScope": "COLLECTION",
      "fields": [
        { "fieldPath": "userId", "order": "ASCENDING" },
        { "fieldPath": "createdAt", "order": "DESCENDING" }
      ]
    },
    {
      "collectionGroup": "aiSafetyLogs",
      "queryScope": "COLLECTION",
      "fields": [
        { "fieldPath": "flagged", "order": "ASCENDING" },
        { "fieldPath": "createdAt", "order": "DESCENDING" }
      ]
    }
  ],
  "fieldOverrides": []
}