{
  "indexes": [
    {
      "collectionGroup": "pressReleases",
      "queryScope": "COLLECTION",
      "fields": [
        { "fieldPath": "status", "order": "ASCENDING" },
        { "fieldPath": "createdAt", "order": "DESCENDING" }
      ]
    },
    {
      "collectionGroup": "pressReleases",
      "queryScope": "COLLECTION",
      "fields": [
        { "fieldPath": "type", "order": "ASCENDING" },
        { "fieldPath": "status", "order": "ASCENDING" },
        { "fieldPath": "createdAt", "order": "DESCENDING" }
      ]
    },
    {
      "collectionGroup": "pressReleases",
      "queryScope": "COLLECTION",
      "fields": [
        { "fieldPath": "campaignId", "order": "ASCENDING" },
        { "fieldPath": "createdAt", "order": "DESCENDING" }
      ]
    },
    {
      "collectionGroup": "prCampaigns",
      "queryScope": "COLLECTION",
      "fields": [
        { "fieldPath": "status", "order": "ASCENDING" },
        { "fieldPath": "startDate", "order": "DESCENDING" }
      ]
    },
    {
      "collectionGroup": "prCampaigns",
      "queryScope": "COLLECTION",
      "fields": [
        { "fieldPath": "type", "order": "ASCENDING" },
        { "fieldPath": "status", "order": "ASCENDING" }
      ]
    },
    {
      "collectionGroup": "pressContacts",
      "queryScope": "COLLECTION",
      "fields": [
        { "fieldPath": "status", "order": "ASCENDING" },
        { "fieldPath": "tier", "order": "ASCENDING" }
      ]
    },
    {
      "collectionGroup": "pressContacts",
      "queryScope": "COLLECTION",
      "fields": [
        { "fieldPath": "status", "order": "ASCENDING" },
        { "fieldPath": "responseRate", "order": "DESCENDING" }
      ]
    },
    {
      "collectionGroup": "pressMentions",
      "queryScope": "COLLECTION",
      "fields": [
        { "fieldPath": "publishedAt", "order": "DESCENDING" },
        { "fieldPath": "sentiment", "order": "ASCENDING" }
      ]
    },
    {
      "collectionGroup": "pressMentions",
      "queryScope": "COLLECTION",
      "fields": [
        { "fieldPath": "isCrisis", "order": "ASCENDING" },
        { "fieldPath": "notifiedAt", "order": "ASCENDING" }
      ]
    },
    {
      "collectionGroup": "pressMentions",
      "queryScope": "COLLECTION",
      "fields": [
        { "fieldPath": "sourceType", "order": "ASCENDING" },
        { "fieldPath": "publishedAt", "order": "DESCENDING" }
      ]
    },
    {
      "collectionGroup": "pressMentions",
      "queryScope": "COLLECTION",
      "fields": [
        { "fieldPath": "sentiment", "order": "ASCENDING" },
        { "fieldPath": "publishedAt", "order": "DESCENDING" }
      ]
    },
    {
      "collectionGroup": "monitoringSources",
      "queryScope": "COLLECTION",
      "fields": [
        { "fieldPath": "type", "order": "ASCENDING" },
        { "fieldPath": "active", "order": "ASCENDING" }
      ]
    },
    {
      "collectionGroup": "influencerApplications",
      "queryScope": "COLLECTION",
      "fields": [
        { "fieldPath": "userId", "order": "ASCENDING" },
        { "fieldPath": "status", "order": "ASCENDING" }
      ]
    },
    {
      "collectionGroup": "influencerApplications",
      "queryScope": "COLLECTION",
      "fields": [
        { "fieldPath": "status", "order": "ASCENDING" },
        { "fieldPath": "appliedAt", "order": "DESCENDING" }
      ]
    },
    {
      "collectionGroup": "influencerProfiles",
      "queryScope": "COLLECTION",
      "fields": [
        { "fieldPath": "status", "order": "ASCENDING" },
        { "fieldPath": "tier", "order": "ASCENDING" }
      ]
    },
    {
      "collectionGroup": "influencerProfiles",
      "queryScope": "COLLECTION",
      "fields": [
        { "fieldPath": "tier", "order": "ASCENDING" },
        { "fieldPath": "totalEarnings", "order": "DESCENDING" }
      ]
    },
    {
      "collectionGroup": "influencerProfiles",
      "queryScope": "COLLECTION",
      "fields": [
        { "fieldPath": "status", "order": "ASCENDING" },
        { "fieldPath": "lifetimeRevenue", "order": "DESCENDING" }
      ]
    },
    {
      "collectionGroup": "influencerContracts",
      "queryScope": "COLLECTION",
      "fields": [
        { "fieldPath": "influencerId", "order": "ASCENDING" },
        { "fieldPath": "status", "order": "ASCENDING" }
      ]
    },
    {
      "collectionGroup": "influencerContracts",
      "queryScope": "COLLECTION",
      "fields": [
        { "fieldPath": "status", "order": "ASCENDING" },
        { "fieldPath": "startDate", "order": "DESCENDING" }
      ]
    },
    {
      "collectionGroup": "influencerPerformance",
      "queryScope": "COLLECTION",
      "fields": [
        { "fieldPath": "influencerId", "order": "ASCENDING" },
        { "fieldPath": "period", "order": "DESCENDING" }
      ]
    },
    {
      "collectionGroup": "influencerPerformance",
      "queryScope": "COLLECTION",
      "fields": [
        { "fieldPath": "period", "order": "ASCENDING" },
        { "fieldPath": "earnings.total", "order": "DESCENDING" }
      ]
    },
    {
      "collectionGroup": "influencerPayouts",
      "queryScope": "COLLECTION",
      "fields": [
        { "fieldPath": "influencerId", "order": "ASCENDING" },
        { "fieldPath": "createdAt", "order": "DESCENDING" }
      ]
    },
    {
      "collectionGroup": "influencerPayouts",
      "queryScope": "COLLECTION",
      "fields": [
        { "fieldPath": "status", "order": "ASCENDING" },
        { "fieldPath": "createdAt", "order": "DESCENDING" }
      ]
    },
    {
      "collectionGroup": "influencerPayouts",
      "queryScope": "COLLECTION",
      "fields": [
        { "fieldPath": "period", "order": "ASCENDING" },
        { "fieldPath": "amount", "order": "DESCENDING" }
      ]
    },
    {
      "collectionGroup": "brandAssets",
      "queryScope": "COLLECTION",
      "fields": [
        { "fieldPath": "type", "order": "ASCENDING" },
        { "fieldPath": "status", "order": "ASCENDING" }
      ]
    },
    {
      "collectionGroup": "brandAssets",
      "queryScope": "COLLECTION",
      "fields": [
        { "fieldPath": "category", "order": "ASCENDING" },
        { "fieldPath": "status", "order": "ASCENDING" }
      ]
    },
    {
      "collectionGroup": "brandAssets",
      "queryScope": "COLLECTION",
      "fields": [
        { "fieldPath": "status", "order": "ASCENDING" },
        { "fieldPath": "createdAt", "order": "DESCENDING" }
      ]
    },
    {
      "collectionGroup": "brandGuidelines",
      "queryScope": "COLLECTION",
      "fields": [
        { "fieldPath": "category", "order": "ASCENDING" },
        { "fieldPath": "status", "order": "ASCENDING" }
      ]
    },
    {
      "collectionGroup": "brandGuidelines",
      "queryScope": "COLLECTION",
      "fields": [
        { "fieldPath": "status", "order": "ASCENDING" },
        { "fieldPath": "updatedAt", "order": "DESCENDING" }
      ]
    },
    {
      "collectionGroup": "brandAuditLogs",
      "queryScope": "COLLECTION",
      "fields": [
        { "fieldPath": "sourceType", "order": "ASCENDING" },
        { "fieldPath": "scanDate", "order": "DESCENDING" }
      ]
    },
    {
      "collectionGroup": "brandAuditLogs",
      "queryScope": "COLLECTION",
      "fields": [
        { "fieldPath": "sourceId", "order": "ASCENDING" },
        { "fieldPath": "scanDate", "order": "DESCENDING" }
      ]
    },
    {
      "collectionGroup": "brandAuditLogs",
      "queryScope": "COLLECTION",
      "fields": [
        { "fieldPath": "status", "order": "ASCENDING" },
        { "fieldPath": "scanDate", "order": "DESCENDING" }
      ]
    },
    {
      "collectionGroup": "localizedPressPacks",
      "queryScope": "COLLECTION",
      "fields": [
        { "fieldPath": "basePackId", "order": "ASCENDING" },
        { "fieldPath": "language", "order": "ASCENDING" }
      ]
    },
    {
      "collectionGroup": "localizedPressPacks",
      "queryScope": "COLLECTION",
      "fields": [
        { "fieldPath": "language", "order": "ASCENDING" },
        { "fieldPath": "status", "order": "ASCENDING" }
      ]
    },
    {
      "collectionGroup": "localizedPressPacks",
      "queryScope": "COLLECTION",
      "fields": [
        { "fieldPath": "region", "order": "ASCENDING" },
        { "fieldPath": "status", "order": "ASCENDING" }
      ]
    },
    {
      "collectionGroup": "creatorMaterials",
      "queryScope": "COLLECTION",
      "fields": [
        { "fieldPath": "language", "order": "ASCENDING" },
        { "fieldPath": "region", "order": "ASCENDING" },
        { "fieldPath": "status", "order": "ASCENDING" }
      ]
    },
    {
      "collectionGroup": "creatorMaterials",
      "queryScope": "COLLECTION",
      "fields": [
        { "fieldPath": "language", "order": "ASCENDING" },
        { "fieldPath": "type", "order": "ASCENDING" },
        { "fieldPath": "status", "order": "ASCENDING" }
      ]
    },
    {
      "collectionGroup": "creatorTestimonials",
      "queryScope": "COLLECTION",
      "fields": [
        { "fieldPath": "language", "order": "ASCENDING" },
        { "fieldPath": "region", "order": "ASCENDING" },
        { "fieldPath": "approved", "order": "ASCENDING" },
        { "fieldPath": "featured", "order": "ASCENDING" }
      ]
    },
    {
      "collectionGroup": "creatorTestimonials",
      "queryScope": "COLLECTION",
      "fields": [
        { "fieldPath": "approved", "order": "ASCENDING" },
        { "fieldPath": "featured", "order": "ASCENDING" },
        { "fieldPath": "createdAt", "order": "DESCENDING" }
      ]
    }
  ],
  "fieldOverrides": []
}
