{
  "indexes": [
    {
      "collectionGroup": "creatorAcademyCourses",
      "queryScope": "COLLECTION",
      "fields": [
        { "fieldPath": "isPublished", "order": "ASCENDING" },
        { "fieldPath": "category", "order": "ASCENDING" },
        { "fieldPath": "createdAt", "order": "DESCENDING" }
      ]
    },
    {
      "collectionGroup": "creatorAcademyCourses",
      "queryScope": "COLLECTION",
      "fields": [
        { "fieldPath": "category", "order": "ASCENDING" },
        { "fieldPath": "level", "order": "ASCENDING" },
        { "fieldPath": "avgRating", "order": "DESCENDING" }
      ]
    },
    {
      "collectionGroup": "creatorAcademyCourses",
      "queryScope": "COLLECTION",
      "fields": [
        { "fieldPath": "isPublished", "order": "ASCENDING" },
        { "fieldPath": "enrollmentCount", "order": "DESCENDING" }
      ]
    },
    {
      "collectionGroup": "creatorAcademyProgress",
      "queryScope": "COLLECTION",
      "fields": [
        { "fieldPath": "userId", "order": "ASCENDING" },
        { "fieldPath": "courseId", "order": "ASCENDING" }
      ]
    },
    {
      "collectionGroup": "creatorAcademyProgress",
      "queryScope": "COLLECTION",
      "fields": [
        { "fieldPath": "userId", "order": "ASCENDING" },
        { "fieldPath": "completedAt", "order": "DESCENDING" }
      ]
    },
    {
      "collectionGroup": "creatorAcademyProgress",
      "queryScope": "COLLECTION",
      "fields": [
        { "fieldPath": "courseId", "order": "ASCENDING" },
        { "fieldPath": "progressPercentage", "order": "DESCENDING" }
      ]
    },
    {
      "collectionGroup": "creatorAcademyProgress",
      "queryScope": "COLLECTION",
      "fields": [
        { "fieldPath": "courseId", "order": "ASCENDING" },
        { "fieldPath": "rating", "order": "DESCENDING" }
      ]
    },
    {
      "collectionGroup": "creatorAcademyCertificates",
      "queryScope": "COLLECTION",
      "fields": [
        { "fieldPath": "userId", "order": "ASCENDING" },
        { "fieldPath": "issuedAt", "order": "DESCENDING" }
      ]
    },
    {
      "collectionGroup": "creatorAcademyCertificates",
      "queryScope": "COLLECTION",
      "fields": [
        { "fieldPath": "userId", "order": "ASCENDING" },
        { "fieldPath": "category", "order": "ASCENDING" },
        { "fieldPath": "isValid", "order": "ASCENDING" }
      ]
    },
    {
      "collectionGroup": "creatorEarningProfiles",
      "queryScope": "COLLECTION",
      "fields": [
        { "fieldPath": "skillTier", "order": "ASCENDING" },
        { "fieldPath": "earningsPotentialScore", "order": "DESCENDING" }
      ]
    },
    {
      "collectionGroup": "creatorEarningProfiles",
      "queryScope": "COLLECTION",
      "fields": [
        { "fieldPath": "burnoutRiskScore", "order": "DESCENDING" },
        { "fieldPath": "lastCalculatedAt", "order": "DESCENDING" }
      ]
    },
    {
      "collectionGroup": "creatorEarningProfiles",
      "queryScope": "COLLECTION",
      "fields": [
        { "fieldPath": "updatedAt", "order": "DESCENDING" }
      ]
    },
    {
      "collectionGroup": "earningsOptimizations",
      "queryScope": "COLLECTION",
      "fields": [
        { "fieldPath": "userId", "order": "ASCENDING" },
        { "fieldPath": "status", "order": "ASCENDING" },
        { "fieldPath": "priority", "order": "DESCENDING" }
      ]
    },
    {
      "collectionGroup": "earningsOptimizations",
      "queryScope": "COLLECTION",
      "fields": [
        { "fieldPath": "userId", "order": "ASCENDING" },
        { "fieldPath": "type", "order": "ASCENDING" },
        { "fieldPath": "createdAt", "order": "DESCENDING" }
      ]
    },
    {
      "collectionGroup": "earningsOptimizations",
      "queryScope": "COLLECTION",
      "fields": [
        { "fieldPath": "userId", "order": "ASCENDING" },
        { "fieldPath": "validUntil", "order": "ASCENDING" }
      ]
    },
    {
      "collectionGroup": "earningsOptimizations",
      "queryScope": "COLLECTION",
      "fields": [
        { "fieldPath": "regionCode", "order": "ASCENDING" },
        { "fieldPath": "status", "order": "ASCENDING" },
        { "fieldPath": "priority", "order": "DESCENDING" }
      ]
    },
    {
      "collectionGroup": "pricingRecommendations",
      "queryScope": "COLLECTION",
      "fields": [
        { "fieldPath": "userId", "order": "ASCENDING" },
        { "fieldPath": "serviceType", "order": "ASCENDING" },
        { "fieldPath": "createdAt", "order": "DESCENDING" }
      ]
    },
    {
      "collectionGroup": "pricingRecommendations",
      "queryScope": "COLLECTION",
      "fields": [
        { "fieldPath": "userId", "order": "ASCENDING" },
        { "fieldPath": "expiresAt", "order": "ASCENDING" }
      ]
    },
    {
      "collectionGroup": "pricingRecommendations",
      "queryScope": "COLLECTION",
      "fields": [
        { "fieldPath": "userId", "order": "ASCENDING" },
        { "fieldPath": "confidenceScore", "order": "DESCENDING" }
      ]
    },
    {
      "collectionGroup": "burnoutAssessments",
      "queryScope": "COLLECTION",
      "fields": [
        { "fieldPath": "userId", "order": "ASCENDING" },
        { "fieldPath": "detectedAt", "order": "DESCENDING" }
      ]
    },
    {
      "collectionGroup": "burnoutAssessments",
      "queryScope": "COLLECTION",
      "fields": [
        { "fieldPath": "userId", "order": "ASCENDING" },
        { "fieldPath": "level", "order": "ASCENDING" },
        { "fieldPath": "score", "order": "DESCENDING" }
      ]
    },
    {
      "collectionGroup": "burnoutAssessments",
      "queryScope": "COLLECTION",
      "fields": [
        { "fieldPath": "level", "order": "ASCENDING" },
        { "fieldPath": "resolvedAt", "order": "ASCENDING" },
        { "fieldPath": "detectedAt", "order": "DESCENDING" }
      ]
    },
    {
      "collectionGroup": "burnoutAssessments",
      "queryScope": "COLLECTION",
      "fields": [
        { "fieldPath": "nextCheckAt", "order": "ASCENDING" }
      ]
    },
    {
      "collectionGroup": "creatorEarningMissions",
      "queryScope": "COLLECTION",
      "fields": [
        { "fieldPath": "userId", "order": "ASCENDING" },
        { "fieldPath": "status", "order": "ASCENDING" },
        { "fieldPath": "endsAt", "order": "ASCENDING" }
      ]
    },
    {
      "collectionGroup": "creatorEarningMissions",
      "queryScope": "COLLECTION",
      "fields": [
        { "fieldPath": "userId", "order": "ASCENDING" },
        { "fieldPath": "type", "order": "ASCENDING" },
        { "fieldPath": "createdAt", "order": "DESCENDING" }
      ]
    },
    {
      "collectionGroup": "creatorEarningMissions",
      "queryScope": "COLLECTION",
      "fields": [
        { "fieldPath": "isGlobal", "order": "ASCENDING" },
        { "fieldPath": "status", "order": "ASCENDING" },
        { "fieldPath": "difficulty", "order": "ASCENDING" }
      ]
    },
    {
      "collectionGroup": "creatorEarningMissions",
      "queryScope": "COLLECTION",
      "fields": [
        { "fieldPath": "regionCode", "order": "ASCENDING" },
        { "fieldPath": "status", "order": "ASCENDING" },
        { "fieldPath": "startsAt", "order": "ASCENDING" }
      ]
    },
    {
      "collectionGroup": "creatorBadges",
      "queryScope": "COLLECTION",
      "fields": [
        { "fieldPath": "userId", "order": "ASCENDING" },
        { "fieldPath": "isVisible", "order": "ASCENDING" },
        { "fieldPath": "displayOrder", "order": "ASCENDING" }
      ]
    },
    {
      "collectionGroup": "creatorBadges",
      "queryScope": "COLLECTION",
      "fields": [
        { "fieldPath": "userId", "order": "ASCENDING" },
        { "fieldPath": "type", "order": "ASCENDING" },
        { "fieldPath": "earnedAt", "order": "DESCENDING" }
      ]
    },
    {
      "collectionGroup": "creatorBadges",
      "queryScope": "COLLECTION",
      "fields": [
        { "fieldPath": "userId", "order": "ASCENDING" },
        { "fieldPath": "isExpired", "order": "ASCENDING" },
        { "fieldPath": "expiresAt", "order": "ASCENDING" }
      ]
    },
    {
      "collectionGroup": "creatorPricing",
      "queryScope": "COLLECTION",
      "fields": [
        { "fieldPath": "isActive", "order": "ASCENDING" },
        { "fieldPath": "regionCode", "order": "ASCENDING" }
      ]
    },
    {
      "collectionGroup": "chatSessions",
      "queryScope": "COLLECTION",
      "fields": [
        { "fieldPath": "creatorId", "order": "ASCENDING" },
        { "fieldPath": "startedAt", "order": "DESCENDING" }
      ]
    },
    {
      "collectionGroup": "callSessions",
      "queryScope": "COLLECTION",
      "fields": [
        { "fieldPath": "creatorId", "order": "ASCENDING" },
        { "fieldPath": "createdAt", "order": "DESCENDING" }
      ]
    },
    {
      "collectionGroup": "events",
      "queryScope": "COLLECTION",
      "fields": [
        { "fieldPath": "creatorId", "order": "ASCENDING" },
        { "fieldPath": "startsAt", "order": "DESCENDING" }
      ]
    },
    {
      "collectionGroup": "transactions",
      "queryScope": "COLLECTION",
      "fields": [
        { "fieldPath": "creatorId", "order": "ASCENDING" },
        { "fieldPath": "type", "order": "ASCENDING" },
        { "fieldPath": "createdAt", "order": "DESCENDING" }
      ]
    },
    {
      "collectionGroup": "transactions",
      "queryScope": "COLLECTION",
      "fields": [
        { "fieldPath": "creatorId", "order": "ASCENDING" },
        { "fieldPath": "status", "order": "ASCENDING" },
        { "fieldPath": "createdAt", "order": "DESCENDING" }
      ]
    },
    {
      "collectionGroup": "ratings",
      "queryScope": "COLLECTION",
      "fields": [
        { "fieldPath": "creatorId", "order": "ASCENDING" },
        { "fieldPath": "createdAt", "order": "DESCENDING" }
      ]
    },
    {
      "collectionGroup": "safetyReports",
      "queryScope": "COLLECTION",
      "fields": [
        { "fieldPath": "reportedUserId", "order": "ASCENDING" },
        { "fieldPath": "createdAt", "order": "DESCENDING" }
      ]
    }
  ],
  "fieldOverrides": []
}
